pyzeebe/__init__.py
pyzeebe/channel/__init__.py
pyzeebe/channel/camunda_cloud_channel.py
pyzeebe/channel/channel_options.py
pyzeebe/channel/insecure_channel.py
pyzeebe/channel/secure_channel.py
pyzeebe/channel/utils.py
pyzeebe/client/__init__.py
pyzeebe/client/client.py
pyzeebe/client/sync_client.py
pyzeebe/errors/__init__.py
pyzeebe/errors/credentials_errors.py
pyzeebe/errors/job_errors.py
pyzeebe/errors/message_errors.py
pyzeebe/errors/process_errors.py
pyzeebe/errors/pyzeebe_errors.py
pyzeebe/errors/zeebe_errors.py
pyzeebe/function_tools/__init__.py
pyzeebe/function_tools/async_tools.py
pyzeebe/function_tools/dict_tools.py
pyzeebe/function_tools/parameter_tools.py
pyzeebe/grpc_internals/__init__.py
pyzeebe/grpc_internals/grpc_utils.py
pyzeebe/grpc_internals/zeebe_adapter.py
pyzeebe/grpc_internals/zeebe_adapter_base.py
pyzeebe/grpc_internals/zeebe_job_adapter.py
pyzeebe/grpc_internals/zeebe_message_adapter.py
pyzeebe/grpc_internals/zeebe_process_adapter.py
pyzeebe/job/__init__.py
pyzeebe/job/job.py
pyzeebe/job/job_status.py
pyzeebe/task/__init__.py
pyzeebe/task/exception_handler.py
pyzeebe/task/task.py
pyzeebe/task/task_builder.py
pyzeebe/task/task_config.py
pyzeebe/task/types.py
pyzeebe/worker/__init__.py
pyzeebe/worker/job_executor.py
pyzeebe/worker/job_poller.py
pyzeebe/worker/task_router.py
pyzeebe/worker/task_state.py
pyzeebe/worker/worker.py
tests/__init__.py
tests/integration/__init__.py
tests/integration/cancel_process_test.py
tests/integration/conftest.py
tests/integration/publish_message_test.py
tests/integration/run_process_test.py
tests/integration/utils/__init__.py
tests/integration/utils/process_run.py
tests/integration/utils/process_stats.py
tests/integration/utils/wait_for_process.py
tests/unit/__init__.py
tests/unit/conftest.py
tests/unit/channel/__init__.py
tests/unit/channel/camunda_cloud_channel_test.py
tests/unit/channel/channel_options_test.py
tests/unit/channel/insecure_channel_test.py
tests/unit/channel/secure_channel_test.py
pyzeebe_lzgabel-8.4.0.1.dist-info/LICENSE.md
pyzeebe_lzgabel-8.4.0.1.dist-info/METADATA
pyzeebe_lzgabel-8.4.0.1.dist-info/WHEEL
pyzeebe_lzgabel-8.4.0.1.dist-info/top_level.txt
pyzeebe_lzgabel-8.4.0.1.dist-info/RECORD
