Metadata-Version: 2.1
Name: pyzeebe-lzgabel
Version: 8.4.0.1
Summary: Custom pyzeebe for lzgabel
Home-page: https://gitlab.com/lzgabel/pyzeebe
Author: Zhi Li
Author-email: lz19960321lz@gmail.com
Classifier: Programming Language :: Python :: 3
Classifier: License :: OSI Approved :: MIT License
Classifier: Operating System :: OS Independent
License-File: LICENSE.md
Requires-Dist: zeebe-grpc ~=8.4.0
